smart_context_selector/__init__.py
smart_context_selector/cli.py
smart_context_selector/core.py
smart_context_selector/configs/n8n.json
smart_context_selector-1.0.0.dist-info/licenses/LICENSE
smart_context_selector-1.0.0.dist-info/METADATA
smart_context_selector-1.0.0.dist-info/WHEEL
smart_context_selector-1.0.0.dist-info/entry_points.txt
smart_context_selector-1.0.0.dist-info/top_level.txt
smart_context_selector-1.0.0.dist-info/RECORD
